{
  "preRequisites:11": [
    811189054
  ],
  "properties:10": {
    "betterquesting:10": {
      "desc:8": "No Description\n\n§3配合HV阶段解锁的进气仓与蒸馏塔，你或许可以准备一些蒸馏液态空气的蒸馏塔来提取资源。",
      "frame:8": "DIAMOND_ON_SQUARE",
      "icon:10": {
        "Count:3": 1,
        "Damage:2": 10002,
        "id:8": "gregtech:mte"
      },
      "name:8": "§b§l真空冷冻机"
    }
  },
  "questID:3": 1009091570,
  "rewards:9": {
    "0:10": {
      "index:3": 0,
      "rewardID:8": "bq_standard:item",
      "rewards:9": {
        "0:10": {
          "Count:3": 1,
          "id:8": "simple_trophies:trophy",
          "tag:10": {
            "TrophyColorBlue:3": 235,
            "TrophyColorGreen:3": 207,
            "TrophyColorRed:3": 180,
            "TrophyItem:10": {
              "Count:1": 1,
              "Damage:2": 10002,
              "id:8": "gregtech:mte"
            },
            "TrophyName:8": "真空冷冻机",
            "TrophyShowsTooltip:1": 1,
            "TrophyVariant:8": "classic"
          }
        }
      }
    },
    "1:10": {
      "index:3": 1,
      "rewardID:8": "bq_standard:item",
      "rewards:9": {}
    }
  },
  "tasks:9": {
    "0:10": {
      "index:3": 1,
      "requiredItems:9": {
        "0:10": {
          "Count:3": 1,
          "Damage:2": 10002,
          "id:8": "gregtech:mte"
        }
      },
      "taskID:8": "bq_standard:retrieval"
    }
  }
}